[ {
  "@id" : 1,
  "schema" : "basicTile",
  "attributes" : [ {
    "@class" : "oogasalad.model.attribute.IntAttribute",
    "key" : "height",
    "value" : 10
  }, {
    "@class" : "oogasalad.model.attribute.PositionAttribute",
    "key" : "position",
    "x" : 100.0,
    "y" : 100.0
  }, {
    "@class" : "oogasalad.model.attribute.IntAttribute",
    "key" : "width",
    "value" : 10
  } ]
}, {
  "@id" : 2,
  "schema" : "basicTile",
  "attributes" : [ {
    "@class" : "oogasalad.model.attribute.IntAttribute",
    "key" : "height",
    "value" : 10
  }, {
    "@class" : "oogasalad.model.attribute.PositionAttribute",
    "key" : "position",
    "x" : 150.0,
    "y" : 100.0
  }, {
    "@class" : "oogasalad.model.attribute.IntAttribute",
    "key" : "width",
    "value" : 10
  } ]
}, {
  "@id" : 3,
  "schema" : "basicTile",
  "attributes" : [ {
    "@class" : "oogasalad.model.attribute.IntAttribute",
    "key" : "height",
    "value" : 10
  }, {
    "@class" : "oogasalad.model.attribute.PositionAttribute",
    "key" : "position",
    "x" : 200.0,
    "y" : 100.0
  }, {
    "@class" : "oogasalad.model.attribute.IntAttribute",
    "key" : "width",
    "value" : 10
  } ]
}, {
  "@id" : 4,
  "schema" : "basicTile",
  "attributes" : [ {
    "@class" : "oogasalad.model.attribute.IntAttribute",
    "key" : "height",
    "value" : 10
  }, {
    "@class" : "oogasalad.model.attribute.PositionAttribute",
    "key" : "position",
    "x" : 200.0,
    "y" : 150.0
  }, {
    "@class" : "oogasalad.model.attribute.IntAttribute",
    "key" : "width",
    "value" : 10
  } ]
}, {
  "@id" : 5,
  "schema" : "basicTile",
  "attributes" : [ {
    "@class" : "oogasalad.model.attribute.IntAttribute",
    "key" : "height",
    "value" : 10
  }, {
    "@class" : "oogasalad.model.attribute.PositionAttribute",
    "key" : "position",
    "x" : 200.0,
    "y" : 200.0
  }, {
    "@class" : "oogasalad.model.attribute.IntAttribute",
    "key" : "width",
    "value" : 10
  } ]
}, {
  "@id" : 6,
  "schema" : "basicTile",
  "attributes" : [ {
    "@class" : "oogasalad.model.attribute.IntAttribute",
    "key" : "height",
    "value" : 10
  }, {
    "@class" : "oogasalad.model.attribute.PositionAttribute",
    "key" : "position",
    "x" : 150.0,
    "y" : 200.0
  }, {
    "@class" : "oogasalad.model.attribute.IntAttribute",
    "key" : "width",
    "value" : 10
  } ]
}, {
  "@id" : 7,
  "schema" : "basicTile",
  "attributes" : [ {
    "@class" : "oogasalad.model.attribute.IntAttribute",
    "key" : "height",
    "value" : 10
  }, {
    "@class" : "oogasalad.model.attribute.PositionAttribute",
    "key" : "position",
    "x" : 100.0,
    "y" : 200.0
  }, {
    "@class" : "oogasalad.model.attribute.IntAttribute",
    "key" : "width",
    "value" : 10
  } ]
}, {
  "@id" : 8,
  "schema" : "basicTile",
  "attributes" : [ {
    "@class" : "oogasalad.model.attribute.IntAttribute",
    "key" : "height",
    "value" : 10
  }, {
    "@class" : "oogasalad.model.attribute.PositionAttribute",
    "key" : "position",
    "x" : 100.0,
    "y" : 150.0
  }, {
    "@class" : "oogasalad.model.attribute.IntAttribute",
    "key" : "width",
    "value" : 10
  } ]
} ]